{
  "disabledtooltip": [],
  "currentlyFocusedSackNumber": 0,
  "currentlySelectedSackNumber": 0,
  "sacks": [
    {
      "iconinfo": null,
      "items": [
        {
          "stackSize": 1,
          "seed": 8211,
          "baseName": "Records\\Item\\EquipmentWeapon\\Club\\U_E_TruncheonofMalice.dbr",
          "prefixName": "",
          "suffixName": "",
          "relicName": "",
          "relicBonus": "",
          "var1": 0,
          "relicName2": "",
          "relicBonus2": "",
          "var2": 2035248,
          "pointX": 0,
          "pointY": 0
        },
        {
          "stackSize": 1,
          "seed": 3746,
          "baseName": "Records\\Item\\EquipmentWeapon\\Club\\U_E_ThornyMaul.dbr",
          "prefixName": "",
          "suffixName": "",
          "relicName": "",
          "relicBonus": "",
          "var1": 0,
          "relicName2": "",
          "relicBonus2": "",
          "var2": 2035248,
          "pointX": 1,
          "pointY": 0
        },
        {
          "stackSize": 1,
          "seed": 3787,
          "baseName": "Records\\Item\\EquipmentWeapon\\Club\\U_E_Spinebreaker.dbr",
          "prefixName": "",
          "suffixName": "",
          "relicName": "",
          "relicBonus": "",
          "var1": 0,
          "relicName2": "",
          "relicBonus2": "",
          "var2": 2035248,
          "pointX": 2,
          "pointY": 0
        },
        {
          "stackSize": 1,
          "seed": 9037,
          "baseName": "Records\\Item\\EquipmentWeapon\\Club\\U_E_LykaionMalleus.dbr",
          "prefixName": "",
          "suffixName": "",
          "relicName": "",
          "relicBonus": "",
          "var1": 0,
          "relicName2": "",
          "relicBonus2": "",
          "var2": 2035248,
          "pointX": 4,
          "pointY": 0
        },
        {
          "stackSize": 1,
          "seed": 6134,
          "baseName": "Records\\Item\\EquipmentWeapon\\Club\\U_E_Demeter'sSorrow.dbr",
          "prefixName": "",
          "suffixName": "",
          "relicName": "",
          "relicBonus": "",
          "var1": 0,
          "relicName2": "",
          "relicBonus2": "",
          "var2": 2035248,
          "pointX": 6,
          "pointY": 0
        },
        {
          "stackSize": 1,
          "seed": 20831,
          "baseName": "records\\item\\equipmentweapon\\club\\u_l_prometheus'gift.dbr",
          "prefixName": "",
          "suffixName": "",
          "relicName": "",
          "relicBonus": "",
          "var1": 0,
          "relicName2": "",
          "relicBonus2": "",
          "var2": 2035248,
          "pointX": 4,
          "pointY": 4
        },
        {
          "stackSize": 1,
          "seed": 1818,
          "baseName": "records\\item\\equipmentweapon\\club\\u_l_orion'smace.dbr",
          "prefixName": "",
          "suffixName": "",
          "relicName": "",
          "relicBonus": "",
          "var1": 0,
          "relicName2": "",
          "relicBonus2": "",
          "var2": 2035248,
          "pointX": 5,
          "pointY": 4
        },
        {
          "stackSize": 1,
          "seed": 6230,
          "baseName": "Records\\Item\\EquipmentWeapon\\Club\\U_L_HandofHephaestus.dbr",
          "prefixName": "",
          "suffixName": "",
          "relicName": "",
          "relicBonus": "",
          "var1": 0,
          "relicName2": "",
          "relicBonus2": "",
          "var2": 2035248,
          "pointX": 17,
          "pointY": 4
        },
        {
          "stackSize": 1,
          "seed": 6230,
          "baseName": "Records\\Item\\EquipmentWeapon\\Club\\U_L_KrakensFist.dbr",
          "prefixName": "",
          "suffixName": "",
          "relicName": "",
          "relicBonus": "",
          "var1": 0,
          "relicName2": "",
          "relicBonus2": "",
          "var2": 2035248,
          "pointX": 15,
          "pointY": 4
        },
        {
          "stackSize": 1,
          "seed": 28588,
          "baseName": "records\\item\\equipmentweapon\\club\\u_l_hornoftiamat.dbr",
          "prefixName": "",
          "suffixName": "",
          "relicName": "",
          "relicBonus": "",
          "var1": 0,
          "relicName2": "",
          "relicBonus2": "",
          "var2": 2035248,
          "pointX": 13,
          "pointY": 4
        },
        {
          "stackSize": 1,
          "seed": 15499,
          "baseName": "records\\item\\equipmentweapon\\club\\u_l_glacialmaul.dbr",
          "prefixName": "",
          "suffixName": "",
          "relicName": "",
          "relicBonus": "",
          "var1": 0,
          "relicName2": "",
          "relicBonus2": "",
          "var2": 2035248,
          "pointX": 7,
          "pointY": 4
        },
        {
          "stackSize": 1,
          "seed": 15137,
          "baseName": "records\\item\\equipmentweapon\\club\\u_l_saprosthecorrupter.dbr",
          "prefixName": "",
          "suffixName": "",
          "relicName": "",
          "relicBonus": "",
          "var1": 0,
          "relicName2": "",
          "relicBonus2": "",
          "var2": 2035248,
          "pointX": 9,
          "pointY": 4
        },
        {
          "stackSize": 1,
          "seed": 2869,
          "baseName": "Records\\Item\\EquipmentWeapon\\Club\\U_L_Areithous'Mace.dbr",
          "prefixName": "",
          "suffixName": "",
          "relicName": "",
          "relicBonus": "",
          "var1": 0,
          "relicName2": "",
          "relicBonus2": "",
          "var2": 2035248,
          "pointX": 11,
          "pointY": 4
        },
        {
          "stackSize": 1,
          "seed": 16,
          "baseName": "records\\item\\equipmentweapon\\club\\u_l_agamemnon'sscepter.dbr",
          "prefixName": "",
          "suffixName": "",
          "relicName": "",
          "relicBonus": "",
          "var1": 0,
          "relicName2": "",
          "relicBonus2": "",
          "var2": 2035248,
          "pointX": 10,
          "pointY": 4
        },
        {
          "stackSize": 1,
          "seed": 29612,
          "baseName": "records\\item\\equipmentweapon\\club\\u_l_scepterofthanatos.dbr",
          "prefixName": "",
          "suffixName": "",
          "relicName": "",
          "relicBonus": "",
          "var1": 0,
          "relicName2": "",
          "relicBonus2": "",
          "var2": 2035248,
          "pointX": 12,
          "pointY": 4
        },
        {
          "stackSize": 1,
          "seed": 8623,
          "baseName": "Records\\XPack\\Item\\EquipmentWeapons\\Club\\U_E_002.dbr",
          "prefixName": "",
          "suffixName": "",
          "relicName": "",
          "relicBonus": "",
          "var1": 0,
          "relicName2": "",
          "relicBonus2": "",
          "var2": 2035248,
          "pointX": 0,
          "pointY": 4
        },
        {
          "stackSize": 1,
          "seed": 25243,
          "baseName": "records\\xpack\\item\\equipmentweapons\\club\\u_e_001.dbr",
          "prefixName": "",
          "suffixName": "",
          "relicName": "",
          "relicBonus": "",
          "var1": 0,
          "relicName2": "",
          "relicBonus2": "",
          "var2": 2035248,
          "pointX": 2,
          "pointY": 4
        },
        {
          "stackSize": 1,
          "seed": 27509,
          "baseName": "Records\\XPack\\Item\\EquipmentWeapons\\Club\\U_L_001.dbr",
          "prefixName": "",
          "suffixName": "",
          "relicName": "",
          "relicBonus": "",
          "var1": 0,
          "relicName2": "",
          "relicBonus2": "",
          "var2": 2035248,
          "pointX": 2,
          "pointY": 8
        },
        {
          "stackSize": 1,
          "seed": 17599,
          "baseName": "records\\xpack\\item\\equipmentweapons\\club\\u_l_002.dbr",
          "prefixName": "",
          "suffixName": "",
          "relicName": "",
          "relicBonus": "",
          "var1": 0,
          "relicName2": "",
          "relicBonus2": "",
          "var2": 2035248,
          "pointX": 0,
          "pointY": 8
        }
      ]
    },
    {
      "iconinfo": null,
      "items": []
    },
    {
      "iconinfo": null,
      "items": []
    },
    {
      "iconinfo": null,
      "items": []
    },
    {
      "iconinfo": null,
      "items": []
    },
    {
      "iconinfo": null,
      "items": []
    },
    {
      "iconinfo": null,
      "items": []
    },
    {
      "iconinfo": null,
      "items": []
    },
    {
      "iconinfo": null,
      "items": []
    },
    {
      "iconinfo": null,
      "items": []
    },
    {
      "iconinfo": null,
      "items": []
    },
    {
      "iconinfo": null,
      "items": []
    }
  ]
}