{
  "disabledtooltip": [],
  "currentlyFocusedSackNumber": 0,
  "currentlySelectedSackNumber": 3,
  "sacks": [
    {
      "iconinfo": null,
      "items": [
        {
          "stackSize": 1,
          "seed": 30074,
          "baseName": "Records\\Item\\EquipmentArmband\\MI_N_Arachnos.dbr",
          "prefixName": "",
          "suffixName": "",
          "relicName": "",
          "relicBonus": "",
          "var1": 0,
          "relicName2": "",
          "relicBonus2": "",
          "var2": 2035248,
          "pointX": 0,
          "pointY": 0
        },
        {
          "stackSize": 1,
          "seed": 26970,
          "baseName": "Records\\Item\\EquipmentArmband\\MI_N_Boarman.dbr",
          "prefixName": "",
          "suffixName": "",
          "relicName": "",
          "relicBonus": "",
          "var1": 0,
          "relicName2": "",
          "relicBonus2": "",
          "var2": 2035248,
          "pointX": 4,
          "pointY": 0
        },
        {
          "stackSize": 1,
          "seed": 1443,
          "baseName": "Records\\Item\\EquipmentArmband\\MI_N_Wraith.dbr",
          "prefixName": "",
          "suffixName": "",
          "relicName": "",
          "relicBonus": "",
          "var1": 0,
          "relicName2": "",
          "relicBonus2": "",
          "var2": 2035248,
          "pointX": 6,
          "pointY": 0
        },
        {
          "stackSize": 1,
          "seed": 13776,
          "baseName": "Records\\Item\\EquipmentArmband\\MI_N_Mummy.dbr",
          "prefixName": "",
          "suffixName": "",
          "relicName": "",
          "relicBonus": "",
          "var1": 0,
          "relicName2": "",
          "relicBonus2": "",
          "var2": 2035248,
          "pointX": 8,
          "pointY": 0
        },
        {
          "stackSize": 1,
          "seed": 21288,
          "baseName": "Records\\Item\\EquipmentArmband\\MI_N_Reptilian.dbr",
          "prefixName": "",
          "suffixName": "",
          "relicName": "",
          "relicBonus": "",
          "var1": 0,
          "relicName2": "",
          "relicBonus2": "",
          "var2": 2035248,
          "pointX": 10,
          "pointY": 0
        },
        {
          "stackSize": 1,
          "seed": 25082,
          "baseName": "Records\\Item\\EquipmentArmband\\MI_N_JackalmanMelee.dbr",
          "prefixName": "",
          "suffixName": "",
          "relicName": "",
          "relicBonus": "",
          "var1": 0,
          "relicName2": "",
          "relicBonus2": "",
          "var2": 2035248,
          "pointX": 12,
          "pointY": 0
        },
        {
          "stackSize": 1,
          "seed": 24612,
          "baseName": "Records\\Item\\EquipmentArmband\\MI_N_DuneRaider.dbr",
          "prefixName": "",
          "suffixName": "",
          "relicName": "",
          "relicBonus": "",
          "var1": 0,
          "relicName2": "",
          "relicBonus2": "",
          "var2": 2035248,
          "pointX": 14,
          "pointY": 0
        },
        {
          "stackSize": 1,
          "seed": 9789,
          "baseName": "Records\\Item\\EquipmentArmband\\MI_N_JackalmanMelee.dbr",
          "prefixName": "",
          "suffixName": "",
          "relicName": "",
          "relicBonus": "",
          "var1": 0,
          "relicName2": "",
          "relicBonus2": "",
          "var2": 2035248,
          "pointX": 12,
          "pointY": 2
        },
        {
          "stackSize": 1,
          "seed": 3421,
          "baseName": "Records\\Item\\EquipmentArmband\\MI_N_DuneRaider.dbr",
          "prefixName": "",
          "suffixName": "",
          "relicName": "",
          "relicBonus": "",
          "var1": 0,
          "relicName2": "",
          "relicBonus2": "",
          "var2": 2035248,
          "pointX": 14,
          "pointY": 2
        },
        {
          "stackSize": 1,
          "seed": 10082,
          "baseName": "Records\\Item\\EquipmentArmband\\MI_N_JackalmanMelee.dbr",
          "prefixName": "",
          "suffixName": "",
          "relicName": "",
          "relicBonus": "",
          "var1": 0,
          "relicName2": "",
          "relicBonus2": "",
          "var2": 2035248,
          "pointX": 12,
          "pointY": 4
        },
        {
          "stackSize": 1,
          "seed": 1456,
          "baseName": "Records\\Item\\EquipmentArmband\\MI_N_JackalmanMage.dbr",
          "prefixName": "",
          "suffixName": "",
          "relicName": "",
          "relicBonus": "",
          "var1": 0,
          "relicName2": "",
          "relicBonus2": "",
          "var2": 2035248,
          "pointX": 16,
          "pointY": 0
        },
        {
          "stackSize": 1,
          "seed": 25883,
          "baseName": "Records\\Item\\EquipmentArmband\\MI_N_Boarman.dbr",
          "prefixName": "",
          "suffixName": "",
          "relicName": "",
          "relicBonus": "",
          "var1": 0,
          "relicName2": "",
          "relicBonus2": "",
          "var2": 2035248,
          "pointX": 4,
          "pointY": 2
        },
        {
          "stackSize": 1,
          "seed": 16732,
          "baseName": "Records\\Item\\EquipmentArmband\\MI_N_DuneRaider.dbr",
          "prefixName": "",
          "suffixName": "",
          "relicName": "",
          "relicBonus": "",
          "var1": 0,
          "relicName2": "",
          "relicBonus2": "",
          "var2": 2035248,
          "pointX": 14,
          "pointY": 4
        },
        {
          "stackSize": 1,
          "seed": 11743,
          "baseName": "Records\\Item\\EquipmentArmband\\MI_N_Arachnos.dbr",
          "prefixName": "",
          "suffixName": "",
          "relicName": "",
          "relicBonus": "",
          "var1": 0,
          "relicName2": "",
          "relicBonus2": "",
          "var2": 2035248,
          "pointX": 0,
          "pointY": 2
        },
        {
          "stackSize": 1,
          "seed": 18432,
          "baseName": "Records\\Item\\EquipmentArmband\\MI_N_Mummy.dbr",
          "prefixName": "",
          "suffixName": "",
          "relicName": "",
          "relicBonus": "",
          "var1": 0,
          "relicName2": "",
          "relicBonus2": "",
          "var2": 2035248,
          "pointX": 8,
          "pointY": 2
        },
        {
          "stackSize": 1,
          "seed": 20422,
          "baseName": "Records\\Item\\EquipmentArmband\\MI_N_DuneRaider.dbr",
          "prefixName": "",
          "suffixName": "",
          "relicName": "",
          "relicBonus": "",
          "var1": 0,
          "relicName2": "",
          "relicBonus2": "",
          "var2": 2035248,
          "pointX": 14,
          "pointY": 6
        },
        {
          "stackSize": 1,
          "seed": 24879,
          "baseName": "Records\\Item\\EquipmentArmband\\MI_N_Reptilian.dbr",
          "prefixName": "",
          "suffixName": "",
          "relicName": "",
          "relicBonus": "",
          "var1": 0,
          "relicName2": "",
          "relicBonus2": "",
          "var2": 2035248,
          "pointX": 10,
          "pointY": 2
        },
        {
          "stackSize": 1,
          "seed": 19758,
          "baseName": "Records\\Item\\EquipmentArmband\\MI_N_DuneRaider.dbr",
          "prefixName": "",
          "suffixName": "",
          "relicName": "",
          "relicBonus": "",
          "var1": 0,
          "relicName2": "",
          "relicBonus2": "",
          "var2": 2035248,
          "pointX": 14,
          "pointY": 8
        },
        {
          "stackSize": 1,
          "seed": 13993,
          "baseName": "Records\\Item\\EquipmentArmband\\MI_N_Reptilian.dbr",
          "prefixName": "",
          "suffixName": "",
          "relicName": "",
          "relicBonus": "",
          "var1": 0,
          "relicName2": "",
          "relicBonus2": "",
          "var2": 2035248,
          "pointX": 10,
          "pointY": 4
        },
        {
          "stackSize": 1,
          "seed": 256,
          "baseName": "Records\\Item\\EquipmentArmband\\MI_N_JackalmanMage.dbr",
          "prefixName": "",
          "suffixName": "",
          "relicName": "",
          "relicBonus": "",
          "var1": 0,
          "relicName2": "",
          "relicBonus2": "",
          "var2": 2035248,
          "pointX": 16,
          "pointY": 2
        },
        {
          "stackSize": 1,
          "seed": 8915,
          "baseName": "Records\\Item\\EquipmentArmband\\MI_N_Boarman.dbr",
          "prefixName": "",
          "suffixName": "",
          "relicName": "",
          "relicBonus": "",
          "var1": 0,
          "relicName2": "",
          "relicBonus2": "",
          "var2": 2035248,
          "pointX": 4,
          "pointY": 4
        },
        {
          "stackSize": 1,
          "seed": 23018,
          "baseName": "Records\\Item\\EquipmentArmband\\MI_N_JackalmanMelee.dbr",
          "prefixName": "",
          "suffixName": "",
          "relicName": "",
          "relicBonus": "",
          "var1": 0,
          "relicName2": "",
          "relicBonus2": "",
          "var2": 2035248,
          "pointX": 12,
          "pointY": 6
        },
        {
          "stackSize": 1,
          "seed": 14177,
          "baseName": "Records\\Item\\EquipmentArmband\\MI_N_Arachnos.dbr",
          "prefixName": "",
          "suffixName": "",
          "relicName": "",
          "relicBonus": "",
          "var1": 0,
          "relicName2": "",
          "relicBonus2": "",
          "var2": 2035248,
          "pointX": 0,
          "pointY": 4
        },
        {
          "stackSize": 1,
          "seed": 26746,
          "baseName": "Records\\Item\\EquipmentArmband\\MI_N_Boarman.dbr",
          "prefixName": "",
          "suffixName": "",
          "relicName": "",
          "relicBonus": "",
          "var1": 0,
          "relicName2": "",
          "relicBonus2": "",
          "var2": 2035248,
          "pointX": 4,
          "pointY": 6
        },
        {
          "stackSize": 1,
          "seed": 22780,
          "baseName": "Records\\Item\\EquipmentArmband\\MI_N_Wraith.dbr",
          "prefixName": "",
          "suffixName": "",
          "relicName": "",
          "relicBonus": "",
          "var1": 0,
          "relicName2": "",
          "relicBonus2": "",
          "var2": 2035248,
          "pointX": 6,
          "pointY": 2
        },
        {
          "stackSize": 1,
          "seed": 21836,
          "baseName": "Records\\Item\\EquipmentArmband\\MI_N_Wraith.dbr",
          "prefixName": "",
          "suffixName": "",
          "relicName": "",
          "relicBonus": "",
          "var1": 0,
          "relicName2": "",
          "relicBonus2": "",
          "var2": 2035248,
          "pointX": 6,
          "pointY": 4
        },
        {
          "stackSize": 1,
          "seed": 24078,
          "baseName": "Records\\Item\\EquipmentArmband\\MI_N_Arachnos.dbr",
          "prefixName": "",
          "suffixName": "",
          "relicName": "",
          "relicBonus": "",
          "var1": 0,
          "relicName2": "",
          "relicBonus2": "",
          "var2": 2035248,
          "pointX": 0,
          "pointY": 6
        },
        {
          "stackSize": 1,
          "seed": 6198,
          "baseName": "Records\\Item\\EquipmentArmband\\MI_N_SatyrMage.dbr",
          "prefixName": "",
          "suffixName": "",
          "relicName": "",
          "relicBonus": "",
          "var1": 0,
          "relicName2": "",
          "relicBonus2": "",
          "var2": 53407808,
          "pointX": 2,
          "pointY": 0
        },
        {
          "stackSize": 1,
          "seed": 5124,
          "baseName": "Records\\Item\\EquipmentArmband\\MI_N_Arachnos.dbr",
          "prefixName": "",
          "suffixName": "",
          "relicName": "",
          "relicBonus": "",
          "var1": 0,
          "relicName2": "",
          "relicBonus2": "",
          "var2": 53407808,
          "pointX": 0,
          "pointY": 8
        },
        {
          "stackSize": 1,
          "seed": 11336,
          "baseName": "Records\\Item\\EquipmentArmband\\MI_N_Boarman.dbr",
          "prefixName": "",
          "suffixName": "",
          "relicName": "",
          "relicBonus": "",
          "var1": 0,
          "relicName2": "",
          "relicBonus2": "",
          "var2": 53407808,
          "pointX": 4,
          "pointY": 8
        }
      ]
    },
    {
      "iconinfo": null,
      "items": [
        {
          "stackSize": 1,
          "seed": 13047,
          "baseName": "Records\\Item\\EquipmentArmband\\MI_N_GoldenSkeleton.dbr",
          "prefixName": "",
          "suffixName": "",
          "relicName": "",
          "relicBonus": "",
          "var1": 0,
          "relicName2": "",
          "relicBonus2": "",
          "var2": 2035248,
          "pointX": 0,
          "pointY": 0
        },
        {
          "stackSize": 1,
          "seed": 4295,
          "baseName": "Records\\Item\\EquipmentArmband\\MI_N_NeanderthalMelee.dbr",
          "prefixName": "",
          "suffixName": "",
          "relicName": "",
          "relicBonus": "",
          "var1": 0,
          "relicName2": "",
          "relicBonus2": "",
          "var2": 2035248,
          "pointX": 2,
          "pointY": 0
        },
        {
          "stackSize": 1,
          "seed": 25289,
          "baseName": "Records\\Item\\EquipmentArmband\\MI_N_NeanderthalMage.dbr",
          "prefixName": "",
          "suffixName": "",
          "relicName": "",
          "relicBonus": "",
          "var1": 0,
          "relicName2": "",
          "relicBonus2": "",
          "var2": 2035248,
          "pointX": 4,
          "pointY": 0
        },
        {
          "stackSize": 1,
          "seed": 21495,
          "baseName": "Records\\Item\\EquipmentArmband\\MI_N_NeanderthalMage.dbr",
          "prefixName": "",
          "suffixName": "",
          "relicName": "",
          "relicBonus": "",
          "var1": 0,
          "relicName2": "",
          "relicBonus2": "",
          "var2": 2035248,
          "pointX": 4,
          "pointY": 2
        },
        {
          "stackSize": 1,
          "seed": 13567,
          "baseName": "Records\\Item\\EquipmentArmband\\MI_N_NeanderthalMelee.dbr",
          "prefixName": "",
          "suffixName": "",
          "relicName": "",
          "relicBonus": "",
          "var1": 0,
          "relicName2": "",
          "relicBonus2": "",
          "var2": 2035248,
          "pointX": 2,
          "pointY": 2
        },
        {
          "stackSize": 1,
          "seed": 10716,
          "baseName": "Records\\Item\\EquipmentArmband\\MI_N_TigermanMelee.dbr",
          "prefixName": "",
          "suffixName": "",
          "relicName": "",
          "relicBonus": "",
          "var1": 0,
          "relicName2": "",
          "relicBonus2": "",
          "var2": 2035248,
          "pointX": 6,
          "pointY": 0
        },
        {
          "stackSize": 1,
          "seed": 21479,
          "baseName": "Records\\Item\\EquipmentArmband\\MI_N_TropicalArachnos.dbr",
          "prefixName": "",
          "suffixName": "",
          "relicName": "",
          "relicBonus": "",
          "var1": 0,
          "relicName2": "",
          "relicBonus2": "",
          "var2": 2035248,
          "pointX": 8,
          "pointY": 0
        },
        {
          "stackSize": 1,
          "seed": 29992,
          "baseName": "Records\\Item\\EquipmentArmband\\MI_N_Bandari.dbr",
          "prefixName": "",
          "suffixName": "",
          "relicName": "",
          "relicBonus": "",
          "var1": 0,
          "relicName2": "",
          "relicBonus2": "",
          "var2": 2035248,
          "pointX": 10,
          "pointY": 0
        },
        {
          "stackSize": 1,
          "seed": 2685,
          "baseName": "Records\\Item\\EquipmentArmband\\MI_N_TigermanMelee.dbr",
          "prefixName": "",
          "suffixName": "",
          "relicName": "",
          "relicBonus": "",
          "var1": 0,
          "relicName2": "",
          "relicBonus2": "",
          "var2": 2035248,
          "pointX": 6,
          "pointY": 2
        },
        {
          "stackSize": 1,
          "seed": 26592,
          "baseName": "Records\\Item\\EquipmentArmband\\MI_N_TigermanMelee.dbr",
          "prefixName": "",
          "suffixName": "",
          "relicName": "",
          "relicBonus": "",
          "var1": 0,
          "relicName2": "",
          "relicBonus2": "",
          "var2": 2035248,
          "pointX": 6,
          "pointY": 4
        },
        {
          "stackSize": 1,
          "seed": 25568,
          "baseName": "Records\\XPack\\Item\\EquipmentArmor\\Armband\\MI_N_AnouranMelee.dbr",
          "prefixName": "",
          "suffixName": "",
          "relicName": "",
          "relicBonus": "",
          "var1": 0,
          "relicName2": "",
          "relicBonus2": "",
          "var2": 2035248,
          "pointX": 12,
          "pointY": 0
        },
        {
          "stackSize": 1,
          "seed": 23625,
          "baseName": "Records\\XPack3\\Items\\EquipmentArmor\\Armband\\MI_N_MonkeymanMelee.dbr",
          "prefixName": "",
          "suffixName": "",
          "relicName": "",
          "relicBonus": "",
          "var1": 0,
          "relicName2": "",
          "relicBonus2": "",
          "var2": 2035248,
          "pointX": 14,
          "pointY": 0
        },
        {
          "stackSize": 1,
          "seed": 390,
          "baseName": "Records\\XPack3\\Items\\EquipmentArmor\\Armband\\MI_N_EmbalmedPriestMage.dbr",
          "prefixName": "",
          "suffixName": "",
          "relicName": "",
          "relicBonus": "",
          "var1": 0,
          "relicName2": "",
          "relicBonus2": "",
          "var2": 2035248,
          "pointX": 16,
          "pointY": 0
        },
        {
          "stackSize": 1,
          "seed": 31603,
          "baseName": "Records\\XPack\\Item\\EquipmentArmor\\Armband\\MI_N_AnouranMelee.dbr",
          "prefixName": "",
          "suffixName": "",
          "relicName": "",
          "relicBonus": "",
          "var1": 0,
          "relicName2": "",
          "relicBonus2": "",
          "var2": 2035248,
          "pointX": 12,
          "pointY": 2
        },
        {
          "stackSize": 1,
          "seed": 30353,
          "baseName": "Records\\Item\\EquipmentArmband\\MI_N_NeanderthalMelee.dbr",
          "prefixName": "",
          "suffixName": "",
          "relicName": "",
          "relicBonus": "",
          "var1": 0,
          "relicName2": "",
          "relicBonus2": "",
          "var2": 2035248,
          "pointX": 2,
          "pointY": 4
        },
        {
          "stackSize": 1,
          "seed": 27183,
          "baseName": "Records\\Item\\EquipmentArmband\\MI_N_NeanderthalMage.dbr",
          "prefixName": "",
          "suffixName": "",
          "relicName": "",
          "relicBonus": "",
          "var1": 0,
          "relicName2": "",
          "relicBonus2": "",
          "var2": 2035248,
          "pointX": 4,
          "pointY": 4
        },
        {
          "stackSize": 1,
          "seed": 20417,
          "baseName": "Records\\Item\\EquipmentArmband\\MI_N_GoldenSkeleton.dbr",
          "prefixName": "",
          "suffixName": "",
          "relicName": "",
          "relicBonus": "",
          "var1": 0,
          "relicName2": "",
          "relicBonus2": "",
          "var2": 2035248,
          "pointX": 0,
          "pointY": 2
        },
        {
          "stackSize": 1,
          "seed": 19327,
          "baseName": "Records\\Item\\EquipmentArmband\\MI_N_NeanderthalMelee.dbr",
          "prefixName": "",
          "suffixName": "",
          "relicName": "",
          "relicBonus": "",
          "var1": 0,
          "relicName2": "",
          "relicBonus2": "",
          "var2": 2035248,
          "pointX": 2,
          "pointY": 6
        },
        {
          "stackSize": 1,
          "seed": 20480,
          "baseName": "Records\\Item\\EquipmentArmband\\MI_N_NeanderthalMelee.dbr",
          "prefixName": "",
          "suffixName": "",
          "relicName": "",
          "relicBonus": "",
          "var1": 0,
          "relicName2": "",
          "relicBonus2": "",
          "var2": 2035248,
          "pointX": 2,
          "pointY": 8
        },
        {
          "stackSize": 1,
          "seed": 115,
          "baseName": "Records\\Item\\EquipmentArmband\\MI_N_NeanderthalMage.dbr",
          "prefixName": "",
          "suffixName": "",
          "relicName": "",
          "relicBonus": "",
          "var1": 0,
          "relicName2": "",
          "relicBonus2": "",
          "var2": 2035248,
          "pointX": 4,
          "pointY": 6
        },
        {
          "stackSize": 1,
          "seed": 22373,
          "baseName": "Records\\Item\\EquipmentArmband\\MI_N_NeanderthalMelee.dbr",
          "prefixName": "",
          "suffixName": "",
          "relicName": "",
          "relicBonus": "",
          "var1": 0,
          "relicName2": "",
          "relicBonus2": "",
          "var2": 2035248,
          "pointX": 2,
          "pointY": 10
        },
        {
          "stackSize": 1,
          "seed": 3333,
          "baseName": "Records\\Item\\EquipmentArmband\\MI_N_TropicalArachnos.dbr",
          "prefixName": "",
          "suffixName": "",
          "relicName": "",
          "relicBonus": "",
          "var1": 0,
          "relicName2": "",
          "relicBonus2": "",
          "var2": 2035248,
          "pointX": 8,
          "pointY": 2
        },
        {
          "stackSize": 1,
          "seed": 7954,
          "baseName": "Records\\XPack3\\Items\\EquipmentArmor\\Armband\\MI_N_MonkeymanMelee.dbr",
          "prefixName": "",
          "suffixName": "",
          "relicName": "",
          "relicBonus": "",
          "var1": 0,
          "relicName2": "",
          "relicBonus2": "",
          "var2": 2035248,
          "pointX": 14,
          "pointY": 2
        },
        {
          "stackSize": 1,
          "seed": 1456,
          "baseName": "Records\\Item\\EquipmentArmband\\MI_N_NeanderthalMage.dbr",
          "prefixName": "",
          "suffixName": "",
          "relicName": "",
          "relicBonus": "",
          "var1": 0,
          "relicName2": "",
          "relicBonus2": "",
          "var2": 2035248,
          "pointX": 4,
          "pointY": 8
        },
        {
          "stackSize": 1,
          "seed": 21295,
          "baseName": "Records\\Item\\EquipmentArmband\\MI_N_NeanderthalMage.dbr",
          "prefixName": "",
          "suffixName": "",
          "relicName": "",
          "relicBonus": "",
          "var1": 0,
          "relicName2": "",
          "relicBonus2": "",
          "var2": 2035248,
          "pointX": 4,
          "pointY": 10
        },
        {
          "stackSize": 1,
          "seed": 14177,
          "baseName": "Records\\Item\\EquipmentArmband\\MI_N_NeanderthalMelee.dbr",
          "prefixName": "",
          "suffixName": "",
          "relicName": "",
          "relicBonus": "",
          "var1": 0,
          "relicName2": "",
          "relicBonus2": "",
          "var2": 2035248,
          "pointX": 2,
          "pointY": 12
        }
      ]
    },
    {
      "iconinfo": null,
      "items": [
        {
          "stackSize": 1,
          "seed": 1975,
          "baseName": "Records\\XPack3\\Items\\EquipmentArmor\\Armband\\MI_N_EmbalmedPriestMelee.dbr",
          "prefixName": "",
          "suffixName": "",
          "relicName": "",
          "relicBonus": "",
          "var1": 0,
          "relicName2": "",
          "relicBonus2": "",
          "var2": 2035248,
          "pointX": 0,
          "pointY": 0
        },
        {
          "stackSize": 1,
          "seed": 4706,
          "baseName": "Records\\XPack3\\Items\\EquipmentArmor\\Armband\\MI_N_SerpentoidMage.dbr",
          "prefixName": "",
          "suffixName": "",
          "relicName": "",
          "relicBonus": "",
          "var1": 0,
          "relicName2": "",
          "relicBonus2": "",
          "var2": 2035248,
          "pointX": 2,
          "pointY": 0
        },
        {
          "stackSize": 1,
          "seed": 19733,
          "baseName": "Records\\XPack3\\Items\\EquipmentArmor\\Armband\\MI_N_PotamoiWarriorMelee.dbr",
          "prefixName": "",
          "suffixName": "",
          "relicName": "",
          "relicBonus": "",
          "var1": 0,
          "relicName2": "",
          "relicBonus2": "",
          "var2": 2035248,
          "pointX": 4,
          "pointY": 0
        },
        {
          "stackSize": 1,
          "seed": 22663,
          "baseName": "Records\\XPack3\\Items\\EquipmentArmor\\Armband\\MI_N_TritonWarriorMelee.dbr",
          "prefixName": "",
          "suffixName": "",
          "relicName": "",
          "relicBonus": "",
          "var1": 0,
          "relicName2": "",
          "relicBonus2": "",
          "var2": 2035248,
          "pointX": 6,
          "pointY": 0
        },
        {
          "stackSize": 1,
          "seed": 13372,
          "baseName": "Records\\XPack3\\Items\\EquipmentArmor\\Armband\\MI_N_TritonWarriorMelee.dbr",
          "prefixName": "",
          "suffixName": "",
          "relicName": "",
          "relicBonus": "",
          "var1": 0,
          "relicName2": "",
          "relicBonus2": "",
          "var2": 2035248,
          "pointX": 6,
          "pointY": 2
        },
        {
          "stackSize": 1,
          "seed": 4537,
          "baseName": "Records\\XPack3\\Items\\EquipmentArmor\\Armband\\MI_N_SerpentoidMelee.dbr",
          "prefixName": "",
          "suffixName": "",
          "relicName": "",
          "relicBonus": "",
          "var1": 0,
          "relicName2": "",
          "relicBonus2": "",
          "var2": 2035248,
          "pointX": 8,
          "pointY": 0
        },
        {
          "stackSize": 1,
          "seed": 31991,
          "baseName": "Records\\XPack3\\Items\\EquipmentArmor\\Armband\\MI_N_SerpentoidMage.dbr",
          "prefixName": "",
          "suffixName": "",
          "relicName": "",
          "relicBonus": "",
          "var1": 0,
          "relicName2": "",
          "relicBonus2": "",
          "var2": 2035248,
          "pointX": 2,
          "pointY": 2
        },
        {
          "stackSize": 1,
          "seed": 5058,
          "baseName": "Records\\XPack3\\Items\\EquipmentArmor\\Armband\\MI_N_TritonWarriorMelee.dbr",
          "prefixName": "",
          "suffixName": "",
          "relicName": "",
          "relicBonus": "",
          "var1": 0,
          "relicName2": "",
          "relicBonus2": "",
          "var2": 2035248,
          "pointX": 6,
          "pointY": 4
        },
        {
          "stackSize": 1,
          "seed": 32388,
          "baseName": "Records\\XPack3\\Items\\EquipmentArmor\\Armband\\MI_N_PotamoiWarriorMelee.dbr",
          "prefixName": "",
          "suffixName": "",
          "relicName": "",
          "relicBonus": "",
          "var1": 0,
          "relicName2": "",
          "relicBonus2": "",
          "var2": 2035248,
          "pointX": 4,
          "pointY": 2
        },
        {
          "stackSize": 1,
          "seed": 5980,
          "baseName": "Records\\XPack3\\Items\\EquipmentArmor\\Armband\\MI_N_SerpentoidMelee.dbr",
          "prefixName": "",
          "suffixName": "",
          "relicName": "",
          "relicBonus": "",
          "var1": 0,
          "relicName2": "",
          "relicBonus2": "",
          "var2": 2035248,
          "pointX": 8,
          "pointY": 2
        },
        {
          "stackSize": 1,
          "seed": 23055,
          "baseName": "Records\\XPack3\\Items\\EquipmentArmor\\Armband\\MI_N_SerpentoidMelee.dbr",
          "prefixName": "",
          "suffixName": "",
          "relicName": "",
          "relicBonus": "",
          "var1": 0,
          "relicName2": "",
          "relicBonus2": "",
          "var2": 2035248,
          "pointX": 8,
          "pointY": 4
        },
        {
          "stackSize": 1,
          "seed": 25062,
          "baseName": "Records\\XPack3\\Items\\EquipmentArmor\\Armband\\MI_N_TritonWitchMage.dbr",
          "prefixName": "",
          "suffixName": "",
          "relicName": "",
          "relicBonus": "",
          "var1": 0,
          "relicName2": "",
          "relicBonus2": "",
          "var2": 2035248,
          "pointX": 12,
          "pointY": 0
        },
        {
          "stackSize": 1,
          "seed": 536,
          "baseName": "Records\\XPack3\\Items\\EquipmentArmor\\Armband\\MI_N_CoralGuardianMelee.dbr",
          "prefixName": "",
          "suffixName": "",
          "relicName": "",
          "relicBonus": "",
          "var1": 0,
          "relicName2": "",
          "relicBonus2": "",
          "var2": 2035248,
          "pointX": 14,
          "pointY": 0
        },
        {
          "stackSize": 1,
          "seed": 14550,
          "baseName": "Records\\XPack\\Item\\EquipmentArmor\\Armband\\MI_N_LamiaMelee.dbr",
          "prefixName": "",
          "suffixName": "",
          "relicName": "",
          "relicBonus": "",
          "var1": 0,
          "relicName2": "",
          "relicBonus2": "",
          "var2": 2035248,
          "pointX": 16,
          "pointY": 0
        },
        {
          "stackSize": 1,
          "seed": 27201,
          "baseName": "Records\\XPack\\Item\\EquipmentArmor\\Armband\\MI_N_LamiaMelee.dbr",
          "prefixName": "",
          "suffixName": "",
          "relicName": "",
          "relicBonus": "",
          "var1": 0,
          "relicName2": "",
          "relicBonus2": "",
          "var2": 2035248,
          "pointX": 16,
          "pointY": 2
        },
        {
          "stackSize": 1,
          "seed": 12219,
          "baseName": "Records\\XPack3\\Items\\EquipmentArmor\\Armband\\MI_N_CoralGuardianMelee.dbr",
          "prefixName": "",
          "suffixName": "",
          "relicName": "",
          "relicBonus": "",
          "var1": 0,
          "relicName2": "",
          "relicBonus2": "",
          "var2": 2035248,
          "pointX": 14,
          "pointY": 2
        },
        {
          "stackSize": 1,
          "seed": 32088,
          "baseName": "Records\\XPack3\\Items\\EquipmentArmor\\Armband\\MI_N_PotamoiWarriorMelee.dbr",
          "prefixName": "",
          "suffixName": "",
          "relicName": "",
          "relicBonus": "",
          "var1": 0,
          "relicName2": "",
          "relicBonus2": "",
          "var2": 2035248,
          "pointX": 4,
          "pointY": 4
        },
        {
          "stackSize": 1,
          "seed": 22819,
          "baseName": "Records\\XPack3\\Items\\EquipmentArmor\\Armband\\MI_N_TritonWarriorMelee.dbr",
          "prefixName": "",
          "suffixName": "",
          "relicName": "",
          "relicBonus": "",
          "var1": 0,
          "relicName2": "",
          "relicBonus2": "",
          "var2": 2035248,
          "pointX": 6,
          "pointY": 6
        },
        {
          "stackSize": 1,
          "seed": 8233,
          "baseName": "Records\\XPack3\\Items\\EquipmentArmor\\Armband\\MI_N_TritonWitchMage.dbr",
          "prefixName": "",
          "suffixName": "",
          "relicName": "",
          "relicBonus": "",
          "var1": 0,
          "relicName2": "",
          "relicBonus2": "",
          "var2": 2035248,
          "pointX": 12,
          "pointY": 2
        }
      ]
    },
    {
      "iconinfo": null,
      "items": [
        {
          "stackSize": 1,
          "seed": 2186,
          "baseName": "Records\\XPack\\Item\\EquipmentArmor\\Armband\\MI_N_EmpusaMage.dbr",
          "prefixName": "",
          "suffixName": "",
          "relicName": "",
          "relicBonus": "",
          "var1": 0,
          "relicName2": "",
          "relicBonus2": "",
          "var2": 2035248,
          "pointX": 0,
          "pointY": 0
        },
        {
          "stackSize": 1,
          "seed": 10404,
          "baseName": "Records\\XPack\\Item\\EquipmentArmor\\Armband\\MI_N_TroglodyteMelee.dbr",
          "prefixName": "",
          "suffixName": "",
          "relicName": "",
          "relicBonus": "",
          "var1": 0,
          "relicName2": "",
          "relicBonus2": "",
          "var2": 2035248,
          "pointX": 2,
          "pointY": 0
        },
        {
          "stackSize": 1,
          "seed": 7803,
          "baseName": "Records\\XPack\\Item\\EquipmentArmor\\Armband\\MI_N_MachaeMelee.dbr",
          "prefixName": "",
          "suffixName": "",
          "relicName": "",
          "relicBonus": "",
          "var1": 0,
          "relicName2": "",
          "relicBonus2": "",
          "var2": 2035248,
          "pointX": 4,
          "pointY": 0
        },
        {
          "stackSize": 1,
          "seed": 29854,
          "baseName": "Records\\XPack\\Item\\EquipmentArmor\\Armband\\MI_N_MachaeMelee.dbr",
          "prefixName": "",
          "suffixName": "",
          "relicName": "",
          "relicBonus": "",
          "var1": 0,
          "relicName2": "",
          "relicBonus2": "",
          "var2": 2035248,
          "pointX": 4,
          "pointY": 2
        },
        {
          "stackSize": 1,
          "seed": 6492,
          "baseName": "Records\\XPack\\Item\\EquipmentArmor\\Armband\\MI_N_TroglodyteMelee.dbr",
          "prefixName": "",
          "suffixName": "",
          "relicName": "",
          "relicBonus": "",
          "var1": 0,
          "relicName2": "",
          "relicBonus2": "",
          "var2": 2035248,
          "pointX": 2,
          "pointY": 2
        },
        {
          "stackSize": 1,
          "seed": 18432,
          "baseName": "Records\\XPack\\Item\\EquipmentArmor\\Armband\\MI_N_EmpusaMage.dbr",
          "prefixName": "",
          "suffixName": "",
          "relicName": "",
          "relicBonus": "",
          "var1": 0,
          "relicName2": "",
          "relicBonus2": "",
          "var2": 2035248,
          "pointX": 0,
          "pointY": 2
        },
        {
          "stackSize": 1,
          "seed": 9071,
          "baseName": "Records\\XPack\\Item\\EquipmentArmor\\Armband\\MI_N_MachaeMelee.dbr",
          "prefixName": "",
          "suffixName": "",
          "relicName": "",
          "relicBonus": "",
          "var1": 0,
          "relicName2": "",
          "relicBonus2": "",
          "var2": 2035248,
          "pointX": 4,
          "pointY": 4
        },
        {
          "stackSize": 1,
          "seed": 2663,
          "baseName": "Records\\XPack\\Item\\EquipmentArmor\\Armband\\MI_N_MelinoeMage.dbr",
          "prefixName": "",
          "suffixName": "",
          "relicName": "",
          "relicBonus": "",
          "var1": 0,
          "relicName2": "",
          "relicBonus2": "",
          "var2": 2035248,
          "pointX": 6,
          "pointY": 0
        },
        {
          "stackSize": 1,
          "seed": 5032,
          "baseName": "Records\\XPack\\Item\\EquipmentArmor\\Armband\\MI_N_GigantesMelee.dbr",
          "prefixName": "",
          "suffixName": "",
          "relicName": "",
          "relicBonus": "",
          "var1": 0,
          "relicName2": "",
          "relicBonus2": "",
          "var2": 2035248,
          "pointX": 8,
          "pointY": 0
        },
        {
          "stackSize": 1,
          "seed": 15421,
          "baseName": "Records\\XPack\\Item\\EquipmentArmor\\Armband\\MI_N_MachaeMelee.dbr",
          "prefixName": "",
          "suffixName": "",
          "relicName": "",
          "relicBonus": "",
          "var1": 0,
          "relicName2": "",
          "relicBonus2": "",
          "var2": 2035248,
          "pointX": 4,
          "pointY": 6
        },
        {
          "stackSize": 1,
          "seed": 32141,
          "baseName": "Records\\XPack\\Item\\EquipmentArmor\\Armband\\MI_N_TroglodyteMelee.dbr",
          "prefixName": "",
          "suffixName": "",
          "relicName": "",
          "relicBonus": "",
          "var1": 0,
          "relicName2": "",
          "relicBonus2": "",
          "var2": 2035248,
          "pointX": 2,
          "pointY": 4
        },
        {
          "stackSize": 1,
          "seed": 20208,
          "baseName": "records\\xpack2\\item\\equipmentarmor\\armband\\mi_n_troll.dbr",
          "prefixName": "",
          "suffixName": "",
          "relicName": "",
          "relicBonus": "",
          "var1": 0,
          "relicName2": "",
          "relicBonus2": "",
          "var2": 2035248,
          "pointX": 10,
          "pointY": 0
        },
        {
          "stackSize": 1,
          "seed": 27898,
          "baseName": "records\\xpack2\\item\\equipmentarmor\\armband\\mi_n_troll.dbr",
          "prefixName": "",
          "suffixName": "",
          "relicName": "",
          "relicBonus": "",
          "var1": 0,
          "relicName2": "",
          "relicBonus2": "",
          "var2": 2035248,
          "pointX": 10,
          "pointY": 2
        },
        {
          "stackSize": 1,
          "seed": 23741,
          "baseName": "records\\xpack2\\item\\equipmentarmor\\armband\\mi_n_kelpie.dbr",
          "prefixName": "",
          "suffixName": "",
          "relicName": "",
          "relicBonus": "",
          "var1": 0,
          "relicName2": "",
          "relicBonus2": "",
          "var2": 2035248,
          "pointX": 12,
          "pointY": 0
        },
        {
          "stackSize": 1,
          "seed": 9142,
          "baseName": "records\\xpack2\\item\\equipmentarmor\\armband\\mi_n_nerthusshaman.dbr",
          "prefixName": "",
          "suffixName": "",
          "relicName": "",
          "relicBonus": "",
          "var1": 0,
          "relicName2": "",
          "relicBonus2": "",
          "var2": 2035248,
          "pointX": 14,
          "pointY": 0
        },
        {
          "stackSize": 1,
          "seed": 15881,
          "baseName": "records\\xpack2\\item\\equipmentarmor\\armband\\mi_n_troll.dbr",
          "prefixName": "",
          "suffixName": "",
          "relicName": "",
          "relicBonus": "",
          "var1": 0,
          "relicName2": "",
          "relicBonus2": "",
          "var2": 2035248,
          "pointX": 10,
          "pointY": 4
        },
        {
          "stackSize": 1,
          "seed": 29052,
          "baseName": "Records\\Item\\EquipmentArmband\\MI_N_GorgonMelee.dbr",
          "prefixName": "",
          "suffixName": "",
          "relicName": "",
          "relicBonus": "",
          "var1": 0,
          "relicName2": "",
          "relicBonus2": "",
          "var2": 2035248,
          "pointX": 16,
          "pointY": 0
        },
        {
          "stackSize": 1,
          "seed": 30980,
          "baseName": "records\\xpack2\\item\\equipmentarmor\\armband\\mi_n_troll.dbr",
          "prefixName": "",
          "suffixName": "",
          "relicName": "",
          "relicBonus": "",
          "var1": 0,
          "relicName2": "",
          "relicBonus2": "",
          "var2": 2035248,
          "pointX": 10,
          "pointY": 6
        },
        {
          "stackSize": 1,
          "seed": 31661,
          "baseName": "Records\\Item\\EquipmentArmband\\MI_N_GorgonMelee.dbr",
          "prefixName": "",
          "suffixName": "",
          "relicName": "",
          "relicBonus": "",
          "var1": 0,
          "relicName2": "",
          "relicBonus2": "",
          "var2": 2035248,
          "pointX": 16,
          "pointY": 2
        },
        {
          "stackSize": 1,
          "seed": 31661,
          "baseName": "Records\\Item\\EquipmentArmband\\MI_N_GorgonMelee.dbr",
          "prefixName": "",
          "suffixName": "",
          "relicName": "",
          "relicBonus": "",
          "var1": 0,
          "relicName2": "",
          "relicBonus2": "",
          "var2": 2035248,
          "pointX": 16,
          "pointY": 4
        },
        {
          "stackSize": 1,
          "seed": 21965,
          "baseName": "Records\\Item\\EquipmentArmband\\MI_N_GorgonMelee.dbr",
          "prefixName": "",
          "suffixName": "",
          "relicName": "",
          "relicBonus": "",
          "var1": 0,
          "relicName2": "",
          "relicBonus2": "",
          "var2": 2035248,
          "pointX": 16,
          "pointY": 6
        },
        {
          "stackSize": 1,
          "seed": 10591,
          "baseName": "Records\\Item\\EquipmentArmband\\MI_N_GorgonMelee.dbr",
          "prefixName": "",
          "suffixName": "",
          "relicName": "",
          "relicBonus": "",
          "var1": 0,
          "relicName2": "",
          "relicBonus2": "",
          "var2": 53407808,
          "pointX": 16,
          "pointY": 8
        }
      ]
    },
    {
      "iconinfo": null,
      "items": [
        {
          "stackSize": 1,
          "seed": 23426,
          "baseName": "records\\xpack2\\item\\equipmentarmor\\armband\\mi_n_draugr.dbr",
          "prefixName": "Records\\Item\\LootMagicalAffixes\\Prefix\\Default\\Character_ReducedEquipReq_01.dbr",
          "suffixName": "Records\\XPack\\Item\\LootMagicalAffixes\\Suffix\\Default\\Defensive_ResistSleep_01.dbr",
          "relicName": "",
          "relicBonus": "",
          "var1": 0,
          "relicName2": "",
          "relicBonus2": "",
          "var2": 2035248,
          "pointX": 0,
          "pointY": 0
        },
        {
          "stackSize": 1,
          "seed": 8034,
          "baseName": "records\\xpack2\\item\\equipmentarmor\\armband\\mi_n_yerren.dbr",
          "prefixName": "Records\\Item\\LootMagicalAffixes\\Prefix\\Default\\Character_AttributeEnergy_02.dbr",
          "suffixName": "Records\\Item\\LootMagicalAffixes\\Suffix\\Default\\Character_AttributeLife_03.dbr",
          "relicName": "",
          "relicBonus": "",
          "var1": 0,
          "relicName2": "",
          "relicBonus2": "",
          "var2": 2035248,
          "pointX": 2,
          "pointY": 0
        },
        {
          "stackSize": 1,
          "seed": 31769,
          "baseName": "records\\xpack2\\item\\equipmentarmor\\armband\\mi_n_fjordmelee.dbr",
          "prefixName": "Records\\Item\\LootMagicalAffixes\\Prefix\\Default\\Defensive_ResistPierce_03.dbr",
          "suffixName": "Records\\Item\\LootMagicalAffixes\\Suffix\\Default\\Character_AttributeEnergy_02.dbr",
          "relicName": "",
          "relicBonus": "",
          "var1": 0,
          "relicName2": "",
          "relicBonus2": "",
          "var2": 2035248,
          "pointX": 4,
          "pointY": 0
        },
        {
          "stackSize": 1,
          "seed": 31519,
          "baseName": "records\\xpack2\\item\\equipmentarmor\\armband\\mi_n_fjordmage.dbr",
          "prefixName": "Records\\XPack\\Item\\LootMagicalAffixes\\Prefix\\Default\\Rare_AllResists_01.dbr",
          "suffixName": "",
          "relicName": "",
          "relicBonus": "",
          "var1": 0,
          "relicName2": "",
          "relicBonus2": "",
          "var2": 2035248,
          "pointX": 6,
          "pointY": 0
        },
        {
          "stackSize": 1,
          "seed": 30218,
          "baseName": "records\\xpack2\\item\\equipmentarmor\\armband\\mi_n_yerren.dbr",
          "prefixName": "Records\\Item\\LootMagicalAffixes\\Prefix\\Default\\Defensive_Protection_04.dbr",
          "suffixName": "Records\\Item\\LootMagicalAffixes\\Suffix\\Default\\Retaliation_Pierce_01.dbr",
          "relicName": "",
          "relicBonus": "",
          "var1": 0,
          "relicName2": "",
          "relicBonus2": "",
          "var2": 2035248,
          "pointX": 2,
          "pointY": 2
        },
        {
          "stackSize": 1,
          "seed": 6769,
          "baseName": "records\\xpack2\\item\\equipmentarmor\\armband\\mi_n_dvergrmelee.dbr",
          "prefixName": "Records\\Item\\LootMagicalAffixes\\Prefix\\Default\\Defensive_ResistLightning_02.dbr",
          "suffixName": "Records\\Item\\LootMagicalAffixes\\Suffix\\Default\\Character_RegenLife_02.dbr",
          "relicName": "",
          "relicBonus": "",
          "var1": 0,
          "relicName2": "",
          "relicBonus2": "",
          "var2": 2035248,
          "pointX": 8,
          "pointY": 0
        },
        {
          "stackSize": 1,
          "seed": 32033,
          "baseName": "records\\xpack2\\item\\equipmentarmor\\armband\\mi_n_einherjar.dbr",
          "prefixName": "Records\\Item\\LootMagicalAffixes\\Prefix\\Default\\Character_AttributeEnergy_02.dbr",
          "suffixName": "Records\\Item\\LootMagicalAffixes\\Suffix\\Default\\Character_AttributeEnergy_03.dbr",
          "relicName": "",
          "relicBonus": "",
          "var1": 0,
          "relicName2": "",
          "relicBonus2": "",
          "var2": 2035248,
          "pointX": 10,
          "pointY": 0
        },
        {
          "stackSize": 1,
          "seed": 7079,
          "baseName": "records\\xpack2\\item\\equipmentarmor\\armband\\mi_n_alfr.dbr",
          "prefixName": "Records\\Item\\LootMagicalAffixes\\Prefix\\Default\\Character_AttributeEnergy_02.dbr",
          "suffixName": "",
          "relicName": "",
          "relicBonus": "",
          "var1": 0,
          "relicName2": "",
          "relicBonus2": "",
          "var2": 2035248,
          "pointX": 12,
          "pointY": 0
        },
        {
          "stackSize": 1,
          "seed": 15616,
          "baseName": "records\\xpack2\\item\\equipmentarmor\\armband\\mi_n_dvergrmelee.dbr",
          "prefixName": "",
          "suffixName": "Records\\Item\\LootMagicalAffixes\\Suffix\\Default\\Character_AttributeDexterity_03.dbr",
          "relicName": "",
          "relicBonus": "",
          "var1": 0,
          "relicName2": "",
          "relicBonus2": "",
          "var2": 2035248,
          "pointX": 8,
          "pointY": 2
        },
        {
          "stackSize": 1,
          "seed": 14096,
          "baseName": "records\\xpack2\\item\\equipmentarmor\\armband\\mi_n_eldjotun.dbr",
          "prefixName": "Records\\Item\\LootMagicalAffixes\\Prefix\\Default\\Defensive_ResistMulti_LightningCold_03.dbr",
          "suffixName": "Records\\XPack\\Item\\LootMagicalAffixes\\Suffix\\Default\\Defensive_ResistSlow_01.dbr",
          "relicName": "",
          "relicBonus": "",
          "var1": 0,
          "relicName2": "",
          "relicBonus2": "",
          "var2": 2035248,
          "pointX": 14,
          "pointY": 0
        },
        {
          "stackSize": 1,
          "seed": 24145,
          "baseName": "records\\xpack2\\item\\equipmentarmor\\armband\\mi_n_dvergrmelee.dbr",
          "prefixName": "Records\\Item\\LootMagicalAffixes\\Prefix\\Default\\Defensive_ResistCold_02.dbr",
          "suffixName": "Records\\Item\\LootMagicalAffixes\\Suffix\\Default\\Character_RegenLife_02.dbr",
          "relicName": "",
          "relicBonus": "",
          "var1": 0,
          "relicName2": "",
          "relicBonus2": "",
          "var2": 2035248,
          "pointX": 8,
          "pointY": 4
        },
        {
          "stackSize": 1,
          "seed": 30363,
          "baseName": "records\\xpack2\\item\\equipmentarmor\\armband\\mi_n_alfr.dbr",
          "prefixName": "Records\\Item\\LootMagicalAffixes\\Prefix\\Default\\Defensive_Protection_04.dbr",
          "suffixName": "Records\\Item\\LootMagicalAffixes\\Suffix\\Default\\Retaliation_Pierce_01.dbr",
          "relicName": "",
          "relicBonus": "",
          "var1": 0,
          "relicName2": "",
          "relicBonus2": "",
          "var2": 2035248,
          "pointX": 12,
          "pointY": 2
        },
        {
          "stackSize": 1,
          "seed": 31304,
          "baseName": "Records\\Item\\EquipmentArmband\\MI_N_Djinn.dbr",
          "prefixName": "Records\\Item\\LootMagicalAffixes\\Prefix\\Default\\Character_AttributeEnergy_02.dbr",
          "suffixName": "Records\\Item\\LootMagicalAffixes\\Suffix\\Default\\Character_AttributeLife_02.dbr",
          "relicName": "",
          "relicBonus": "",
          "var1": 0,
          "relicName2": "",
          "relicBonus2": "",
          "var2": 2035248,
          "pointX": 16,
          "pointY": 0
        }
      ]
    },
    {
      "iconinfo": null,
      "items": [
        {
          "stackSize": 1,
          "seed": 30235,
          "baseName": "Records\\Item\\EquipmentArmband\\MI_N_Telkine.dbr",
          "prefixName": "Records\\Item\\LootMagicalAffixes\\Prefix\\Default\\Defensive_ResistFire_01.dbr",
          "suffixName": "Records\\Item\\LootMagicalAffixes\\Suffix\\Default\\Character_AttributeLife_01.dbr",
          "relicName": "",
          "relicBonus": "",
          "var1": 0,
          "relicName2": "",
          "relicBonus2": "",
          "var2": 2035248,
          "pointX": 0,
          "pointY": 0
        },
        {
          "stackSize": 1,
          "seed": 12598,
          "baseName": "Records\\Item\\EquipmentArmband\\MI_N_Djinn.dbr",
          "prefixName": "",
          "suffixName": "Records\\Item\\LootMagicalAffixes\\Suffix\\Default\\Character_AttributeStrength_02.dbr",
          "relicName": "",
          "relicBonus": "",
          "var1": 0,
          "relicName2": "",
          "relicBonus2": "",
          "var2": 2035248,
          "pointX": 2,
          "pointY": 0
        },
        {
          "stackSize": 1,
          "seed": 21738,
          "baseName": "Records\\XPack3\\Items\\EquipmentArmor\\Armband\\MI_N_HesperideMage.dbr",
          "prefixName": "",
          "suffixName": "Records\\Item\\LootMagicalAffixes\\Suffix\\Default\\Rare_Glade_Armor_01.dbr",
          "relicName": "",
          "relicBonus": "",
          "var1": 0,
          "relicName2": "",
          "relicBonus2": "",
          "var2": 2035248,
          "pointX": 4,
          "pointY": 0
        }
      ]
    },
    {
      "iconinfo": null,
      "items": []
    },
    {
      "iconinfo": null,
      "items": []
    },
    {
      "iconinfo": null,
      "items": []
    },
    {
      "iconinfo": null,
      "items": []
    },
    {
      "iconinfo": null,
      "items": []
    },
    {
      "iconinfo": null,
      "items": []
    }
  ]
}