{
  "disabledtooltip": [],
  "currentlyFocusedSackNumber": 0,
  "currentlySelectedSackNumber": 6,
  "sacks": [
    {
      "iconinfo": null,
      "items": [
        {
          "stackSize": 1,
          "seed": 19772,
          "baseName": "records\\item\\equipmentgreaves\\mi_l_wraith.dbr",
          "prefixName": "",
          "suffixName": "",
          "relicName": "",
          "relicBonus": "",
          "var1": 0,
          "relicName2": "",
          "relicBonus2": "",
          "var2": 2035248,
          "pointX": 0,
          "pointY": 0
        },
        {
          "stackSize": 1,
          "seed": 24418,
          "baseName": "records\\item\\equipmentgreaves\\mi_l_mummy.dbr",
          "prefixName": "",
          "suffixName": "",
          "relicName": "",
          "relicBonus": "",
          "var1": 0,
          "relicName2": "",
          "relicBonus2": "",
          "var2": 2035248,
          "pointX": 2,
          "pointY": 0
        },
        {
          "stackSize": 1,
          "seed": 19272,
          "baseName": "records\\item\\equipmentgreaves\\mi_l_neanderthalmage.dbr",
          "prefixName": "",
          "suffixName": "",
          "relicName": "",
          "relicBonus": "",
          "var1": 0,
          "relicName2": "",
          "relicBonus2": "",
          "var2": 2035248,
          "pointX": 4,
          "pointY": 0
        },
        {
          "stackSize": 1,
          "seed": 4306,
          "baseName": "records\\item\\equipmentgreaves\\mi_l_bandari.dbr",
          "prefixName": "",
          "suffixName": "",
          "relicName": "",
          "relicBonus": "",
          "var1": 0,
          "relicName2": "",
          "relicBonus2": "",
          "var2": 2035248,
          "pointX": 6,
          "pointY": 0
        }
      ]
    },
    {
      "iconinfo": null,
      "items": [
        {
          "stackSize": 1,
          "seed": 25648,
          "baseName": "records\\xpack\\item\\equipmentarmor\\greaves\\mi_l_anouranmage.dbr",
          "prefixName": "",
          "suffixName": "",
          "relicName": "",
          "relicBonus": "",
          "var1": 0,
          "relicName2": "",
          "relicBonus2": "",
          "var2": 2035248,
          "pointX": 6,
          "pointY": 0
        },
        {
          "stackSize": 1,
          "seed": 434,
          "baseName": "records\\xpack\\item\\equipmentarmor\\greaves\\mi_l_keresmage.dbr",
          "prefixName": "",
          "suffixName": "",
          "relicName": "",
          "relicBonus": "",
          "var1": 0,
          "relicName2": "",
          "relicBonus2": "",
          "var2": 2035248,
          "pointX": 8,
          "pointY": 0
        },
        {
          "stackSize": 1,
          "seed": 27357,
          "baseName": "records\\xpack\\item\\equipmentarmor\\greaves\\mi_l_formicidmage02.dbr",
          "prefixName": "",
          "suffixName": "",
          "relicName": "",
          "relicBonus": "",
          "var1": 0,
          "relicName2": "",
          "relicBonus2": "",
          "var2": 2035248,
          "pointX": 12,
          "pointY": 0
        },
        {
          "stackSize": 1,
          "seed": 29654,
          "baseName": "records\\xpack\\item\\equipmentarmor\\greaves\\mi_l_melinoemage.dbr",
          "prefixName": "",
          "suffixName": "",
          "relicName": "",
          "relicBonus": "",
          "var1": 0,
          "relicName2": "",
          "relicBonus2": "",
          "var2": 2035248,
          "pointX": 16,
          "pointY": 0
        },
        {
          "stackSize": 1,
          "seed": 27484,
          "baseName": "records\\xpack\\item\\equipmentarmor\\greaves\\mi_l_empusamage.dbr",
          "prefixName": "",
          "suffixName": "",
          "relicName": "",
          "relicBonus": "",
          "var1": 0,
          "relicName2": "",
          "relicBonus2": "",
          "var2": 2035248,
          "pointX": 10,
          "pointY": 0
        },
        {
          "stackSize": 1,
          "seed": 10413,
          "baseName": "records\\xpack\\item\\equipmentarmor\\greaves\\mi_l_formicidmage01.dbr",
          "prefixName": "",
          "suffixName": "",
          "relicName": "",
          "relicBonus": "",
          "var1": 0,
          "relicName2": "",
          "relicBonus2": "",
          "var2": 2035248,
          "pointX": 4,
          "pointY": 0
        }
      ]
    },
    {
      "iconinfo": null,
      "items": []
    },
    {
      "iconinfo": null,
      "items": [
        {
          "stackSize": 1,
          "seed": 17327,
          "baseName": "records\\item\\equipmentgreaves\\mi_l_duneraider.dbr",
          "prefixName": "",
          "suffixName": "",
          "relicName": "",
          "relicBonus": "",
          "var1": 0,
          "relicName2": "",
          "relicBonus2": "",
          "var2": 2035248,
          "pointX": 0,
          "pointY": 0
        },
        {
          "stackSize": 1,
          "seed": 18160,
          "baseName": "Records\\Item\\EquipmentGreaves\\MI_L_GoldenSkeleton.dbr",
          "prefixName": "",
          "suffixName": "",
          "relicName": "",
          "relicBonus": "",
          "var1": 0,
          "relicName2": "",
          "relicBonus2": "",
          "var2": 2035248,
          "pointX": 2,
          "pointY": 0
        },
        {
          "stackSize": 1,
          "seed": 21404,
          "baseName": "Records\\Item\\EquipmentGreaves\\MI_L_GoldenSkeleton.dbr",
          "prefixName": "",
          "suffixName": "",
          "relicName": "",
          "relicBonus": "",
          "var1": 0,
          "relicName2": "",
          "relicBonus2": "",
          "var2": 2035248,
          "pointX": 2,
          "pointY": 2
        },
        {
          "stackSize": 1,
          "seed": 13315,
          "baseName": "records\\item\\equipmentgreaves\\mi_e_goldenskeleton.dbr",
          "prefixName": "",
          "suffixName": "",
          "relicName": "",
          "relicBonus": "",
          "var1": 0,
          "relicName2": "",
          "relicBonus2": "",
          "var2": 2035248,
          "pointX": 2,
          "pointY": 4
        },
        {
          "stackSize": 1,
          "seed": 18160,
          "baseName": "Records\\Item\\EquipmentGreaves\\MI_L_GoldenSkeleton.dbr",
          "prefixName": "",
          "suffixName": "",
          "relicName": "",
          "relicBonus": "",
          "var1": 0,
          "relicName2": "",
          "relicBonus2": "",
          "var2": 2035248,
          "pointX": 2,
          "pointY": 6
        },
        {
          "stackSize": 1,
          "seed": 8204,
          "baseName": "Records\\Item\\EquipmentGreaves\\MI_L_GoldenSkeleton.dbr",
          "prefixName": "",
          "suffixName": "",
          "relicName": "",
          "relicBonus": "",
          "var1": 0,
          "relicName2": "",
          "relicBonus2": "",
          "var2": 2035248,
          "pointX": 2,
          "pointY": 8
        },
        {
          "stackSize": 1,
          "seed": 24599,
          "baseName": "Records\\Item\\EquipmentGreaves\\MI_L_GoldenSkeleton.dbr",
          "prefixName": "",
          "suffixName": "",
          "relicName": "",
          "relicBonus": "",
          "var1": 0,
          "relicName2": "",
          "relicBonus2": "",
          "var2": 2035248,
          "pointX": 2,
          "pointY": 10
        },
        {
          "stackSize": 1,
          "seed": 21404,
          "baseName": "Records\\Item\\EquipmentGreaves\\MI_L_GoldenSkeleton.dbr",
          "prefixName": "",
          "suffixName": "",
          "relicName": "",
          "relicBonus": "",
          "var1": 0,
          "relicName2": "",
          "relicBonus2": "",
          "var2": 2035248,
          "pointX": 2,
          "pointY": 12
        },
        {
          "stackSize": 1,
          "seed": 25318,
          "baseName": "Records\\Item\\EquipmentGreaves\\MI_L_GoldenSkeleton.dbr",
          "prefixName": "",
          "suffixName": "",
          "relicName": "",
          "relicBonus": "",
          "var1": 0,
          "relicName2": "",
          "relicBonus2": "",
          "var2": 2035248,
          "pointX": 2,
          "pointY": 14
        },
        {
          "stackSize": 1,
          "seed": 26363,
          "baseName": "records\\item\\equipmentgreaves\\mi_l_goldenskeleton.dbr",
          "prefixName": "",
          "suffixName": "",
          "relicName": "",
          "relicBonus": "",
          "var1": 0,
          "relicName2": "",
          "relicBonus2": "",
          "var2": 2035248,
          "pointX": 2,
          "pointY": 16
        },
        {
          "stackSize": 1,
          "seed": 25318,
          "baseName": "Records\\Item\\EquipmentGreaves\\MI_L_GoldenSkeleton.dbr",
          "prefixName": "",
          "suffixName": "",
          "relicName": "",
          "relicBonus": "",
          "var1": 0,
          "relicName2": "",
          "relicBonus2": "",
          "var2": 2035248,
          "pointX": 2,
          "pointY": 18
        },
        {
          "stackSize": 1,
          "seed": 24599,
          "baseName": "Records\\Item\\EquipmentGreaves\\MI_L_GoldenSkeleton.dbr",
          "prefixName": "",
          "suffixName": "",
          "relicName": "",
          "relicBonus": "",
          "var1": 0,
          "relicName2": "",
          "relicBonus2": "",
          "var2": 2035248,
          "pointX": 4,
          "pointY": 18
        },
        {
          "stackSize": 1,
          "seed": 21404,
          "baseName": "Records\\Item\\EquipmentGreaves\\MI_L_GoldenSkeleton.dbr",
          "prefixName": "",
          "suffixName": "",
          "relicName": "",
          "relicBonus": "",
          "var1": 0,
          "relicName2": "",
          "relicBonus2": "",
          "var2": 2035248,
          "pointX": 6,
          "pointY": 18
        },
        {
          "stackSize": 1,
          "seed": 21404,
          "baseName": "Records\\Item\\EquipmentGreaves\\MI_L_GoldenSkeleton.dbr",
          "prefixName": "",
          "suffixName": "",
          "relicName": "",
          "relicBonus": "",
          "var1": 0,
          "relicName2": "",
          "relicBonus2": "",
          "var2": 2035248,
          "pointX": 8,
          "pointY": 18
        },
        {
          "stackSize": 1,
          "seed": 8204,
          "baseName": "Records\\Item\\EquipmentGreaves\\MI_L_GoldenSkeleton.dbr",
          "prefixName": "",
          "suffixName": "",
          "relicName": "",
          "relicBonus": "",
          "var1": 0,
          "relicName2": "",
          "relicBonus2": "",
          "var2": 2035248,
          "pointX": 10,
          "pointY": 18
        },
        {
          "stackSize": 1,
          "seed": 836,
          "baseName": "records\\item\\equipmentgreaves\\mi_l_neanderthalmelee.dbr",
          "prefixName": "",
          "suffixName": "",
          "relicName": "",
          "relicBonus": "",
          "var1": 0,
          "relicName2": "",
          "relicBonus2": "",
          "var2": 2035248,
          "pointX": 4,
          "pointY": 0
        },
        {
          "stackSize": 1,
          "seed": 4330,
          "baseName": "records\\item\\equipmentgreaves\\mi_l_ratmanchampion.dbr",
          "prefixName": "",
          "suffixName": "",
          "relicName": "",
          "relicBonus": "",
          "var1": 0,
          "relicName2": "",
          "relicBonus2": "",
          "var2": 2035248,
          "pointX": 8,
          "pointY": 0
        },
        {
          "stackSize": 1,
          "seed": 21049,
          "baseName": "records\\xpack\\item\\equipmentarmor\\greaves\\mi_l_anouranmelee.dbr",
          "prefixName": "",
          "suffixName": "",
          "relicName": "",
          "relicBonus": "",
          "var1": 0,
          "relicName2": "",
          "relicBonus2": "",
          "var2": 2035248,
          "pointX": 14,
          "pointY": 0
        },
        {
          "stackSize": 1,
          "seed": 23089,
          "baseName": "records\\item\\equipmentgreaves\\mi_l_yerren.dbr",
          "prefixName": "",
          "suffixName": "",
          "relicName": "",
          "relicBonus": "",
          "var1": 0,
          "relicName2": "",
          "relicBonus2": "",
          "var2": 2035248,
          "pointX": 10,
          "pointY": 0
        }
      ]
    },
    {
      "iconinfo": null,
      "items": [
        {
          "stackSize": 1,
          "seed": 12623,
          "baseName": "records\\xpack\\item\\equipmentarmor\\greaves\\mi_l_machaemelee.dbr",
          "prefixName": "",
          "suffixName": "",
          "relicName": "",
          "relicBonus": "",
          "var1": 0,
          "relicName2": "",
          "relicBonus2": "",
          "var2": 2035248,
          "pointX": 6,
          "pointY": 0
        },
        {
          "stackSize": 1,
          "seed": 1813,
          "baseName": "records\\xpack\\item\\equipmentarmor\\greaves\\mi_l_formicidmelee01.dbr",
          "prefixName": "",
          "suffixName": "",
          "relicName": "",
          "relicBonus": "",
          "var1": 0,
          "relicName2": "",
          "relicBonus2": "",
          "var2": 2035248,
          "pointX": 0,
          "pointY": 0
        },
        {
          "stackSize": 1,
          "seed": 28943,
          "baseName": "records\\xpack\\item\\equipmentarmor\\greaves\\mi_l_formicidmelee02.dbr",
          "prefixName": "",
          "suffixName": "",
          "relicName": "",
          "relicBonus": "",
          "var1": 0,
          "relicName2": "",
          "relicBonus2": "",
          "var2": 2035248,
          "pointX": 4,
          "pointY": 0
        },
        {
          "stackSize": 1,
          "seed": 1008,
          "baseName": "records\\xpack\\item\\equipmentarmor\\greaves\\mi_l_troglodytemelee.dbr",
          "prefixName": "",
          "suffixName": "",
          "relicName": "",
          "relicBonus": "",
          "var1": 0,
          "relicName2": "",
          "relicBonus2": "",
          "var2": 2035248,
          "pointX": 10,
          "pointY": 0
        },
        {
          "stackSize": 1,
          "seed": 26237,
          "baseName": "records\\xpack\\item\\equipmentarmor\\greaves\\mi_l_gigantesmelee.dbr",
          "prefixName": "",
          "suffixName": "",
          "relicName": "",
          "relicBonus": "",
          "var1": 0,
          "relicName2": "",
          "relicBonus2": "",
          "var2": 2035248,
          "pointX": 16,
          "pointY": 0
        }
      ]
    },
    {
      "iconinfo": null,
      "items": [
        {
          "stackSize": 1,
          "seed": 18887,
          "baseName": "records\\xpack\\item\\equipmentarmor\\greaves\\mi_l_gigantesmelee02.dbr",
          "prefixName": "",
          "suffixName": "",
          "relicName": "",
          "relicBonus": "",
          "var1": 0,
          "relicName2": "",
          "relicBonus2": "",
          "var2": 2035248,
          "pointX": 4,
          "pointY": 0
        }
      ]
    },
    {
      "iconinfo": null,
      "items": [
        {
          "stackSize": 1,
          "seed": 21799,
          "baseName": "records\\item\\equipmentgreaves\\mi_l_tigermanmelee.dbr",
          "prefixName": "",
          "suffixName": "",
          "relicName": "",
          "relicBonus": "",
          "var1": 0,
          "relicName2": "",
          "relicBonus2": "",
          "var2": 2035248,
          "pointX": 0,
          "pointY": 0
        }
      ]
    },
    {
      "iconinfo": null,
      "items": []
    },
    {
      "iconinfo": null,
      "items": []
    },
    {
      "iconinfo": null,
      "items": []
    },
    {
      "iconinfo": null,
      "items": []
    },
    {
      "iconinfo": null,
      "items": []
    }
  ]
}