{
  "disabledtooltip": [],
  "currentlyFocusedSackNumber": 0,
  "currentlySelectedSackNumber": 1,
  "sacks": [
    {
      "iconinfo": null,
      "items": [
        {
          "stackSize": 1,
          "seed": 6376,
          "baseName": "Records\\XPack\\Item\\EquipmentArmor\\Torso\\US_N_001.dbr",
          "prefixName": "",
          "suffixName": "",
          "relicName": "",
          "relicBonus": "",
          "var1": 0,
          "relicName2": "",
          "relicBonus2": "",
          "var2": 1065353216,
          "pointX": 0,
          "pointY": 0
        },
        {
          "stackSize": 1,
          "seed": 14208,
          "baseName": "Records\\XPack\\Item\\EquipmentArmor\\Helm\\US_N_001.dbr",
          "prefixName": "",
          "suffixName": "",
          "relicName": "",
          "relicBonus": "",
          "var1": 0,
          "relicName2": "",
          "relicBonus2": "",
          "var2": 1065353216,
          "pointX": 0,
          "pointY": 3
        },
        {
          "stackSize": 1,
          "seed": 16846,
          "baseName": "Records\\XPack\\Item\\EquipmentArmor\\Armband\\US_N_001.dbr",
          "prefixName": "",
          "suffixName": "",
          "relicName": "",
          "relicBonus": "",
          "var1": 0,
          "relicName2": "",
          "relicBonus2": "",
          "var2": 15,
          "pointX": 0,
          "pointY": 5
        },
        {
          "stackSize": 1,
          "seed": 5823,
          "baseName": "Records\\XPack\\Item\\EquipmentArmor\\Greaves\\US_N_001.dbr",
          "prefixName": "",
          "suffixName": "",
          "relicName": "",
          "relicBonus": "",
          "var1": 0,
          "relicName2": "",
          "relicBonus2": "",
          "var2": 1065353216,
          "pointX": 0,
          "pointY": 7
        },
        {
          "stackSize": 1,
          "seed": 28500,
          "baseName": "Records\\XPack\\Item\\equipmentWeapons\\Shield\\US_N_001.dbr",
          "prefixName": "",
          "suffixName": "",
          "relicName": "",
          "relicBonus": "",
          "var1": 0,
          "relicName2": "",
          "relicBonus2": "",
          "var2": 1065353216,
          "pointX": 0,
          "pointY": 9
        },
        {
          "stackSize": 1,
          "seed": 11431,
          "baseName": "Records\\XPack\\Item\\EquipmentWeapons\\Spear\\US_N_001.dbr",
          "prefixName": "",
          "suffixName": "",
          "relicName": "",
          "relicBonus": "",
          "var1": 0,
          "relicName2": "",
          "relicBonus2": "",
          "var2": 1065353216,
          "pointX": 0,
          "pointY": 12
        }
      ]
    },
    {
      "iconinfo": null,
      "items": [
        {
          "stackSize": 1,
          "seed": 17887,
          "baseName": "Records\\XPack\\Item\\EquipmentArmor\\Torso\\U_N_002.dbr",
          "prefixName": "",
          "suffixName": "",
          "relicName": "",
          "relicBonus": "",
          "var1": 0,
          "relicName2": "",
          "relicBonus2": "",
          "var2": 15,
          "pointX": 0,
          "pointY": 0
        },
        {
          "stackSize": 1,
          "seed": 16618,
          "baseName": "Records\\XPack\\Item\\EquipmentArmor\\Helm\\U_N_002.dbr",
          "prefixName": "",
          "suffixName": "",
          "relicName": "",
          "relicBonus": "",
          "var1": 0,
          "relicName2": "",
          "relicBonus2": "",
          "var2": 15,
          "pointX": 0,
          "pointY": 3
        }
      ]
    },
    {
      "iconinfo": null,
      "items": []
    },
    {
      "iconinfo": null,
      "items": []
    },
    {
      "iconinfo": null,
      "items": []
    },
    {
      "iconinfo": null,
      "items": []
    },
    {
      "iconinfo": null,
      "items": []
    },
    {
      "iconinfo": null,
      "items": []
    },
    {
      "iconinfo": null,
      "items": []
    },
    {
      "iconinfo": null,
      "items": []
    },
    {
      "iconinfo": null,
      "items": []
    },
    {
      "iconinfo": null,
      "items": []
    }
  ]
}