{
  "disabledtooltip": [],
  "currentlyFocusedSackNumber": 0,
  "currentlySelectedSackNumber": 0,
  "sacks": [
    {
      "iconinfo": null,
      "items": [
        {
          "stackSize": 1,
          "seed": 10779,
          "baseName": "Records\\Item\\EquipmentGreaves\\USm_N_Oracle'sGarments.dbr",
          "prefixName": "",
          "suffixName": "",
          "relicName": "",
          "relicBonus": "",
          "var1": 0,
          "relicName2": "",
          "relicBonus2": "",
          "var2": 2035248,
          "pointX": 16,
          "pointY": 0
        },
        {
          "stackSize": 1,
          "seed": 22577,
          "baseName": "Records\\Item\\EquipmentArmband\\USm_N_Oracle'sGarments.dbr",
          "prefixName": "",
          "suffixName": "",
          "relicName": "",
          "relicBonus": "",
          "var1": 0,
          "relicName2": "",
          "relicBonus2": "",
          "var2": 2035248,
          "pointX": 16,
          "pointY": 2
        },
        {
          "stackSize": 1,
          "seed": 7141,
          "baseName": "Records\\Item\\EquipmentHelm\\USm_N_Oracle'sGarments.dbr",
          "prefixName": "",
          "suffixName": "",
          "relicName": "",
          "relicBonus": "",
          "var1": 0,
          "relicName2": "",
          "relicBonus2": "",
          "var2": 2035248,
          "pointX": 16,
          "pointY": 4
        },
        {
          "stackSize": 1,
          "seed": 15665,
          "baseName": "Records\\Item\\EquipmentGreaves\\USm_N_Necromancer'sHabiliment.dbr",
          "prefixName": "",
          "suffixName": "",
          "relicName": "",
          "relicBonus": "",
          "var1": 0,
          "relicName2": "",
          "relicBonus2": "",
          "var2": 2035248,
          "pointX": 0,
          "pointY": 0
        },
        {
          "stackSize": 1,
          "seed": 28627,
          "baseName": "Records\\Item\\EquipmentArmband\\USm_N_Necromancer'sHabiliment.dbr",
          "prefixName": "",
          "suffixName": "",
          "relicName": "",
          "relicBonus": "",
          "var1": 0,
          "relicName2": "",
          "relicBonus2": "",
          "var2": 2035248,
          "pointX": 0,
          "pointY": 2
        },
        {
          "stackSize": 1,
          "seed": 11630,
          "baseName": "Records\\Item\\EquipmentArmband\\USm_N_Necromancer'sHabiliment.dbr",
          "prefixName": "",
          "suffixName": "",
          "relicName": "",
          "relicBonus": "",
          "var1": 0,
          "relicName2": "",
          "relicBonus2": "",
          "var2": 1065353216,
          "pointX": 2,
          "pointY": 2
        }
      ]
    },
    {
      "iconinfo": null,
      "items": [
        {
          "stackSize": 1,
          "seed": 5898,
          "baseName": "Records\\Item\\EquipmentArmband\\US_N_LabyrinthineArmor.dbr",
          "prefixName": "",
          "suffixName": "",
          "relicName": "",
          "relicBonus": "",
          "var1": 0,
          "relicName2": "",
          "relicBonus2": "",
          "var2": 2035248,
          "pointX": 0,
          "pointY": 0
        },
        {
          "stackSize": 1,
          "seed": 8565,
          "baseName": "Records\\Item\\EquipmentShield\\US_N_ThebanPanoply.dbr",
          "prefixName": "",
          "suffixName": "",
          "relicName": "",
          "relicBonus": "",
          "var1": 0,
          "relicName2": "",
          "relicBonus2": "",
          "var2": 2035248,
          "pointX": 16,
          "pointY": 0
        },
        {
          "stackSize": 1,
          "seed": 691,
          "baseName": "Records\\Item\\EquipmentHelm\\US_N_ThebanPanoply.dbr",
          "prefixName": "",
          "suffixName": "",
          "relicName": "",
          "relicBonus": "",
          "var1": 0,
          "relicName2": "",
          "relicBonus2": "",
          "var2": 2035248,
          "pointX": 16,
          "pointY": 2
        },
        {
          "stackSize": 1,
          "seed": 32290,
          "baseName": "Records\\Item\\EquipmentGreaves\\US_N_LabyrinthineArmor.dbr",
          "prefixName": "",
          "suffixName": "",
          "relicName": "",
          "relicBonus": "",
          "var1": 0,
          "relicName2": "",
          "relicBonus2": "",
          "var2": 2035248,
          "pointX": 0,
          "pointY": 6
        },
        {
          "stackSize": 1,
          "seed": 13607,
          "baseName": "Records\\Item\\EquipmentGreaves\\US_N_ThebanPanoply.dbr",
          "prefixName": "",
          "suffixName": "",
          "relicName": "",
          "relicBonus": "",
          "var1": 0,
          "relicName2": "",
          "relicBonus2": "",
          "var2": 2035248,
          "pointX": 16,
          "pointY": 4
        },
        {
          "stackSize": 1,
          "seed": 3206,
          "baseName": "Records\\Item\\EquipmentHelm\\US_N_LabyrinthineArmor.dbr",
          "prefixName": "",
          "suffixName": "",
          "relicName": "",
          "relicBonus": "",
          "var1": 0,
          "relicName2": "",
          "relicBonus2": "",
          "var2": 2035248,
          "pointX": 0,
          "pointY": 2
        },
        {
          "stackSize": 1,
          "seed": 16924,
          "baseName": "Records\\Item\\EquipmentShield\\US_N_LabyrinthineArmor.dbr",
          "prefixName": "",
          "suffixName": "",
          "relicName": "",
          "relicBonus": "",
          "var1": 0,
          "relicName2": "",
          "relicBonus2": "",
          "var2": 2035248,
          "pointX": 0,
          "pointY": 4
        },
        {
          "stackSize": 1,
          "seed": 1441,
          "baseName": "Records\\Item\\EquipmentShield\\US_N_LabyrinthineArmor.dbr",
          "prefixName": "",
          "suffixName": "",
          "relicName": "",
          "relicBonus": "",
          "var1": 0,
          "relicName2": "",
          "relicBonus2": "",
          "var2": 1065353216,
          "pointX": 2,
          "pointY": 4
        }
      ]
    },
    {
      "iconinfo": null,
      "items": [
        {
          "stackSize": 1,
          "seed": 11293,
          "baseName": "Records\\Item\\EquipmentArmband\\US_N_ObsidianArmor.dbr",
          "prefixName": "",
          "suffixName": "",
          "relicName": "",
          "relicBonus": "",
          "var1": 0,
          "relicName2": "",
          "relicBonus2": "",
          "var2": 2035248,
          "pointX": 0,
          "pointY": 0
        },
        {
          "stackSize": 1,
          "seed": 18622,
          "baseName": "Records\\Item\\EquipmentHelm\\US_N_ObsidianArmor.dbr",
          "prefixName": "",
          "suffixName": "",
          "relicName": "",
          "relicBonus": "",
          "var1": 0,
          "relicName2": "",
          "relicBonus2": "",
          "var2": 2035248,
          "pointX": 0,
          "pointY": 2
        }
      ]
    },
    {
      "iconinfo": null,
      "items": []
    },
    {
      "iconinfo": null,
      "items": []
    },
    {
      "iconinfo": null,
      "items": []
    },
    {
      "iconinfo": null,
      "items": []
    },
    {
      "iconinfo": null,
      "items": []
    },
    {
      "iconinfo": null,
      "items": []
    },
    {
      "iconinfo": null,
      "items": []
    },
    {
      "iconinfo": null,
      "items": []
    },
    {
      "iconinfo": null,
      "items": []
    }
  ]
}